{"frames": {

"1.png":
{
	"frame": {"x":1,"y":1,"w":40,"h":46},
	"rotated": false,
	"trimmed": true,
	"spriteSourceSize": {"x":4,"y":0,"w":40,"h":46},
	"sourceSize": {"w":46,"h":46},
	"pivot": {"x":0.5,"y":0.5}
},
"2.png":
{
	"frame": {"x":43,"y":1,"w":40,"h":46},
	"rotated": false,
	"trimmed": true,
	"spriteSourceSize": {"x":4,"y":0,"w":40,"h":46},
	"sourceSize": {"w":46,"h":46},
	"pivot": {"x":0.5,"y":0.5}
},
"3.png":
{
	"frame": {"x":1,"y":1,"w":40,"h":46},
	"rotated": false,
	"trimmed": true,
	"spriteSourceSize": {"x":4,"y":0,"w":40,"h":46},
	"sourceSize": {"w":46,"h":46},
	"pivot": {"x":0.5,"y":0.5}
},
"4.png":
{
	"frame": {"x":85,"y":1,"w":40,"h":46},
	"rotated": false,
	"trimmed": true,
	"spriteSourceSize": {"x":4,"y":0,"w":40,"h":46},
	"sourceSize": {"w":46,"h":46},
	"pivot": {"x":0.5,"y":0.5}
}},
"meta": {
	"app": "http://www.codeandweb.com/texturepacker",
	"version": "1.0",
	"image": "sprite.png",
	"format": "RGBA8888",
	"size": {"w":126,"h":48},
	"scale": "1",
	"smartupdate": "$TexturePacker:SmartUpdate:dea2cc4b827ee4b265d931754370733c:c920dff576c0817d028185222839b886:68d88b3cf7eafc9b5accfffdfb2fda91$"
}
}
